syncqb/__init__.py
syncqb/__init__.pyi
syncqb/json_quickbase.py
syncqb/json_quickbase.pyi
syncqb/qb_client.py
syncqb/qb_client.pyi
syncqb/qb_errors.py
syncqb/qb_errors.pyi
syncqb/quickbase.py
syncqb/quickbase.pyi
syncqb/xml_quickbase.py
syncqb/xml_quickbase.pyi
syncqb-1.0.11.dist-info/LICENSE
syncqb-1.0.11.dist-info/METADATA
syncqb-1.0.11.dist-info/WHEEL
syncqb-1.0.11.dist-info/entry_points.txt
syncqb-1.0.11.dist-info/top_level.txt
syncqb-1.0.11.dist-info/RECORD
