Metadata-Version: 2.1
Name: syncqb
Version: 1.0.11
Summary: A Python SDK for quickbase
Author-email: Jacob Gearhardt <jacob@synctivate.com>
License: Copyright (c) 2018 The Python Packaging Authority
Project-URL: Homepage, https://github.com/Synctivate/quickbase-json-sdk
Classifier: Programming Language :: Python :: 3
Classifier: License :: OSI Approved :: MIT License
Classifier: Operating System :: OS Independent
Requires-Python: >=3.6
License-File: LICENSE
Requires-Dist: requests (>=2.25.1)
Requires-Dist: lxml (>=4.6.3)
Requires-Dist: chardet (>=4.0.0)
